MANIFEST.in
README.rst
setup.py
collective/__init__.py
collective.inviting.egg-info/PKG-INFO
collective.inviting.egg-info/SOURCES.txt
collective.inviting.egg-info/dependency_links.txt
collective.inviting.egg-info/entry_points.txt
collective.inviting.egg-info/namespace_packages.txt
collective.inviting.egg-info/not-zip-safe
collective.inviting.egg-info/requires.txt
collective.inviting.egg-info/top_level.txt
collective/inviting/__init__.py
collective/inviting/adapters.py
collective/inviting/configure.zcml
collective/inviting/interfaces.py
collective/inviting/item.py
collective/inviting/mail.py
collective/inviting/profiles.zcml
collective/inviting/setuphandlers.py
collective/inviting/zope2.py
collective/inviting/browser/__init__.py
collective/inviting/browser/configure.zcml
collective/inviting/browser/event_subscribers.pt
collective/inviting/browser/message.py
collective/inviting/browser/rsvp.pt
collective/inviting/browser/rsvp.py
collective/inviting/browser/subscribers.py
collective/inviting/profiles/default/import_steps.xml
collective/inviting/profiles/default/metadata.xml
collective/inviting/profiles/default/skins.xml
collective/inviting/profiles/default/types.xml
collective/inviting/profiles/default/types/Event.xml
collective/inviting/profiles/uninstall/import_steps.xml
collective/inviting/profiles/uninstall/metadata.xml
collective/inviting/profiles/uninstall/skins.xml
collective/inviting/profiles/uninstall/types.xml
collective/inviting/profiles/uninstall/types/Event.xml
collective/inviting/skins/collective_inviting/collective.inviting.txt
collective/inviting/tests/__init__.py
collective/inviting/tests/layers.py
collective/inviting/tests/test_adapters.py
collective/inviting/tests/test_item_uid.py
collective/inviting/tests/test_profile.py
doc/COPYING.txt
doc/HISTORY.txt
doc/gpl-2.0.txt