Metadata-Version: 1.1
Name: collective.inviting
Version: 0.2
Summary: Plone add-on for event invitations, confirmation.
Home-page: https://github.com/collective/collective.inviting
Author: Sean Upton
Author-email: sean.upton@hsc.utah.edu
License: GPL
Platform: UNKNOWN
Classifier: Programming Language :: Python
Classifier: Framework :: Plone
